Assignments A3 _ and A4 - uPower/A3 - uPower/Module 5 - D Type/Register_read_write.v
/* This module is used to read and write into the 32 bit register file
*/

module read_write_registers(
    output reg [63:0] read_data_1, read_data_2, read_data_3, // The output are two 64-bit binary numbers that contain the data stored in RS and RT
    input [63:0] read_mem_data, write_data, 
    input [4:0] rs, rt, rd, bo, bi, // RS and RT are the read registers and RD (Destination register) is the write register
    input [5:0] po,  // 6 bit po
    input RegRead, RegWrite, MemToReg, clk  // RegRead and RegWrite are signals that indicate whether the instruction needs to read from registers and/or write to a register
);
	
    reg [63:0] registers [31:0];  //The set of 64 bit registers

    //always @(rs, rt, rd, bo, bi)
	always @(rs, rt, rd)
    begin
		//$display("RTRTTRT %64b\n %5b\n",read_mem_data,rd);
        //Read from registers
        if(RegRead)
        begin
            $readmemb("registers.mem", registers);  //Reads all the values stored in the 32 registers
            if(po == 6'd19) begin //branch
                read_data_1 = registers[bo];
                read_data_2 = registers[bi];
            end
            else if(po == 6'd31) begin //xo and x type
                read_data_1 = registers[rs];
                read_data_2 = registers[rt];
            end
            else begin                              //Loads and stores
                // $display("HERE\n");
                read_data_1 = registers[rs];
                read_data_3 = registers[rd];
            end
        end
    end

    always @(read_mem_data, write_data, rd) begin
        if(RegWrite == 1'b1) begin
            $readmemb("registers.mem", registers);  //Reads all the values stored in the 32 registers
            if(MemToReg == 1'b0) begin
				if(po == 6'd34) begin    //Load Byte
					registers[rd] = {{56{1'b0}}, write_data[7:0]};
				end
				else if (po == 6'd40) begin     //Load halfword and Zero
					registers[rd] = {{48{1'b0}}, write_data[15:0]};
				end
				else if (po == 6'd42) begin      //Load halfword with sign extension
					registers[rd] = {{48{write_data[15]}}, write_data[15:0]};
				end 
				else if(po == 6'd32) begin     //Load word
					registers[rd] = {{32{1'b0}}, write_data[31:0]};
				end
				else begin                           //Load doubleword
					registers[rd] = write_data;
				end
			end
			else begin
				if(po == 6'd34) begin    //Load Byte
					registers[rd] = {{56{1'b0}}, read_mem_data[7:0]};
				end
				else if (po == 6'd40) begin     //Load halfword and Zero
					registers[rd] = {{48{1'b0}}, read_mem_data[15:0]};
				end
				else if (po == 6'd42) begin      //Load halfword with sign extension
					registers[rd] = {{48{read_mem_data[15]}}, read_mem_data[15:0]};
				end 
				else if(po == 6'd32) begin     //Load word
					registers[rd] = {{32{1'b0}}, read_mem_data[31:0]};
				end
				else begin                           //Load doubleword
					registers[rd] = read_mem_data;
				end
			end
			
           // $display("Reg 0 : %64b\nReg 1 : %64b\nReg 2 : %64b\nReg 3 : %64b\n",registers[0], registers[1], registers[2], registers[3]);
            $writememb("registers.mem", registers);
        end
    end
    

endmodule

Assignments A3 _ and A4 - uPower/A3 - uPower/Module 7 - Branch/Memory_read_write.v
/* This module is used to read and write the data.mem file(Main Memory)
*/
module read_write_memory (
    output reg [63:0] read_data,
    input [63:0] address, 
    input [63:0] write_data,
    input [4:0] rd, 
    input [5:0] po, 
    input MemWrite, MemRead
);

    reg [63:0] data_mem [0:31];

    always @ (address, MemWrite, write_data) 
    begin
        if(MemWrite) begin
            $readmemb("data.mem", data_mem, 0, 31);
            if(po == 6'd38) begin
                data_mem[address] = {{56{1'b0}}, write_data[7:0]};
            end
            else if(po == 6'd44) begin
                data_mem[address] = {{48{1'b0}}, write_data[15:0]};
            end
            else if(po == 6'd36) begin
                data_mem[address] = {{32{1'b0}}, write_data[31:0]};
            end
            else begin
                data_mem[address] = write_data;
				//$display("CCCCCC %64b\n",data_mem[address]);
				
            end
			//$display("DSFSDS %64b\n",data_mem[address]);
            // Write the updated contents back to the data_mem file
            $writememb("data.mem", data_mem);            
        end
    end

    always @(address)
    begin
        $readmemb("data.mem", data_mem, 0, 31);
        if(MemRead) begin
            read_data = data_mem[address];
			//$display("sdgsfg %64b \n",read_data);
        end
    end
endmodule

Assignments A3 _ and A4 - uPower/A3 - uPower/Module 1 - ALU/ALU64Bit.v
/* Module designed to act as the ALU - takes in the opcode, contents of the registers, shiftAmount, ALUResult and AluSrc signals
   with the signedImm as arguments
*/

module ALU64bit(
    output reg [63:0] ALU_result,
    output reg flag,
	input ALUSrc,
	input [3:0] ALUInput,
    input [63:0] rs_content, rt_content,
	input [63:0] ds 
    //input [5:0] opcode,
    //input [4:0] rs, rt, rd, bo, bi,
    //input [15:0] si, //for d type instructions
    //input [9:0] xox,
    //input [8:0] xoxo,
    //input aa, 
    //input [1:0] xods
);

    reg signed [63:0] temp, signed_rt, signed_rs;
    //reg [63:0] zeroExtendSI, signExtendSI, zeroExtendDS;

    always @(rs_content, rt_content, ds, ALUInput)
    begin

		signed_rs = rs_content;
		if(ALUSrc) begin
			signed_rt = ds; 
		end
		else
			signed_rt = rt_content;
		//$display("YYTYTT %64b\n",signed_rt);
			
            case(ALUInput)
			
                4'b0010 : //ADD
                    begin
                    ALU_result = signed_rs + signed_rt;
                    end

                4'b0110 : //SUB - Subtract
					begin
                    ALU_result = signed_rs - signed_rt;
					if(ALU_result == 0) 
						flag = 1'b1;
					else
						flag = 1'b0;
					end

                4'b0000 : //AND
                    ALU_result = rs_content & rt_content;
					
                4'b0001 : //OR
                    ALU_result = rs_content | rt_content;
					
                4'b1100 : //NOR
                    ALU_result = ~(rs_content | rt_content);
					
                4'b0111 : //SLT - Set less than
                    begin
                        if(signed_rs < signed_rt) begin
                            ALU_result = 1;
                        end else begin
                            ALU_result = 0;
                        end
                    end
			
            endcase
	end
			

//		zeroExtendSI = {{48{1'b0}},si[15:0]};
//		signExtendSI = {{48{si[15]}},si[15:0]};
//		zeroExtendDS = {{50{1'b0}},ds[13:0]};

/*      if(opcode == 6'd31 & xoxo != 9'd0)    //XO Format
      begin
            // $display("ADDING\n");
          case(xoxo)
            9'd266: //ADD
                ALU_result = signed_rs + signed_rt;
            9'd40 : //SUBF
                ALU_result = signed_rt - signed_rs;
          endcase
      end  

      else if(opcode == 6'd31 & xox != 10'd0)   //X Format
      begin

        case(xox)

            10'd28: //AND
                ALU_result = signed_rt & signed_rs;
            10'd476: //NAND
                ALU_result = ~(signed_rs & signed_rt);
            10'd444: //OR
                ALU_result = signed_rs | signed_rt;
            10'd316: //XOR
                ALU_result = signed_rs ^ signed_rt;
            10'd986: //EXTSW
                ALU_result = {{32{signed_rs[31]}}, signed_rs[31:0]};
        endcase
      end

      else if(opcode == 6'd19)      //B Format 
      begin
        if(aa == 1) //BEQ
        begin
          ALU_result = signed_rs - signed_rt;
          if(ALU_result == 0)
              Branch = 1'b1;
          else
              Branch = 1'b0;
        end
        else if(aa == 0) //BNE
        begin
            ALU_result = signed_rs - signed_rt;
            if(ALU_result != 0)
            begin
              Branch = 1'b1;
              ALU_result = 1'b0;
              end
            else
              Branch = 1'b0; 
        end
      end

      else if(opcode == 6'd18) //I Format
            Branch = 1'b1;
    
      else if(si != 15'b0)      //D Format
      begin
        //   $display("ADD");
          case(opcode)

            6'd14: //ADDI
                ALU_result = signed_rs + zeroExtendSI;
            6'd15: //ADDIS
                ALU_result = signed_rs + signExtendSI;
            6'd28: //ANDI
                ALU_result = signed_rs & zeroExtendSI;
            6'd24: //ORI
                ALU_result = signed_rs | zeroExtendSI;
            6'd26: //XORI
                ALU_result = signed_rs ^ zeroExtendSI;
            6'd32: //LW0
                ALU_result = signed_rs + zeroExtendSI;
            6'd36: //SW
                ALU_result = signed_rs + signExtendSI;
            6'd37: //SWU
                ALU_result = signed_rs + signExtendSI;
            6'd40: //LHW
                ALU_result = signed_rs + signExtendSI;
            6'd42: //LHWA
                ALU_result = signed_rs + signExtendSI;
            6'd44: //SHW
                ALU_result = signed_rs + signExtendSI;
            6'd34: //LB0    
                ALU_result = signed_rs + zeroExtendSI;
            6'd38: //SB
                ALU_result = signed_rs + signExtendSI;
          endcase
      end  

      else if(ds != 14'b0)      //DS Format
      begin
        if(opcode == 6'd58)
            ALU_result = signed_rs + zeroExtendDS;
        else if(opcode == 6'd62)
            ALU_result = signed_rs + zeroExtendDS;  
      end
    end*/

    //Display
	initial begin
        $monitor("RS : %64b\n, RT/DS : %64b\nFlag : %1b\n Result : %64b\n", signed_rs, signed_rt, flag, ALU_result);
    end
	
endmodule

Assignments A3 _ and A4 - uPower/A4 - uPower/uPowerALUControl.v
/* This module is used to provide the ALU with the correct signal to perform
the right operation depending on the instruction.
*/

module ALU_Control(
	
	output reg [3:0] ALUInput,
	input [1:0] ALUop, 
    input [9:0] xox,
    input [8:0] xoxo,
    input [1:0] xods
);

	initial begin
		ALUInput = 4'b0000;
	end

    always @(ALUop, xox, xoxo, xods)
    begin
        ALUInput  = 4'b0000;	
	
        if(ALUop == 2'b00) begin // store and load
			ALUInput = 4'b0010; 
        end
        else if(ALUop == 2'b01) begin // branch
            ALUInput  = 4'b0110; 
        end
        else if(ALUop == 2'b10) begin //xo-type and x-type
			if(xoxo == 9'b100001010) begin //add
				ALUInput = 4'b0010;
			end
			if(xoxo == 9'b000101000) begin //subtract
				ALUInput = 4'b0110;
			end
			if(xox == 10'b0000011100) begin //and
				ALUInput = 4'b0000;
			end
			if(xox == 10'b0110111100) begin //or
				ALUInput = 4'b0001;
			end
        end
	end
endmodule

Assignments A3 _ and A4 - uPower/A4 - uPower/uPower_Control_Unit.v
/* Module to behave like the control unit to set the necessary signals for the execution of an 
   instruction -
   1. RegDst - Which field of the instruction is the register to be written to
   2. RegWrite - Write to register file
   3. RegRead - Read from a register
   4. ALUSrc - The source for the second input to the ALU
   5. PCSrc - Source for PC (next instruction to be executed)
   6. MemRead - Read from the main memory
   7. MemWrite - Write to the main memory
   8. MemToReg - Source of write_data (data to be written to the register file)
   9. Branch -  When a branch/jump instruction is used
*/

module control_unit(
    output reg  RegRead,
                RegWrite,
                MemRead,
                MemWrite,
                Branch,
                MemToReg,
                ALUSrc,
                PCSrc,
	output reg [1:0] ALUop,
    input [5:0] po
);

    initial begin
        MemRead  = 1'b0;
        MemWrite = 1'b0;
        RegWrite = 1'b0;
        RegRead  = 1'b0;
        Branch   = 1'b0;
        ALUSrc   = 1'b0;
        PCSrc    = 1'b0;
        MemToReg = 1'b0;
		ALUop	 = 2'b00;
		
    end



    always @(po)
    begin
		//initialize
        MemRead  = 1'b0;
        MemWrite = 1'b0;
        RegWrite = 1'b0;
        RegRead  = 1'b0;
        Branch   = 1'b0;
        ALUSrc   = 1'b0;
        PCSrc    = 1'b0;
        MemToReg = 1'b0;
		ALUop	 = 2'b00;
		
		
        //X OR XO Format
        if(po == 6'd31) 
        begin
		    MemRead  = 1'b0;
			MemWrite = 1'b0;
			RegWrite = 1'b1;
			RegRead  = 1'b1;
			Branch   = 1'b0;
			ALUSrc   = 1'b0;
			PCSrc    = 1'b0;
			MemToReg = 1'b0;
			ALUop	 = 2'b10;
            // $display("HOI\n");
            //RegRead = 1'b1;
            //RegWrite = 1'b1;        
        end
		
        if(po == 6'd58 | po == 6'd32 |po == 6'd40 |po == 6'd42 |po == 6'd34) //loads
        begin
		    MemRead  = 1'b1;
			MemWrite = 1'b0;
			RegWrite = 1'b1;
			RegRead  = 1'b1;
			Branch   = 1'b0;
			ALUSrc   = 1'b1;
			PCSrc    = 1'b0;
			MemToReg = 1'b1;
			ALUop	 = 2'b00;
		end
		
		if(po == 6'd38 |po == 6'd44 |po == 6'd37 |po == 6'd36 |po == 6'd62) //stores
        begin
		    MemRead  = 1'b0;
			MemWrite = 1'b1;
			RegWrite = 1'b0;
			RegRead  = 1'b1;
			Branch   = 1'b0;
			ALUSrc   = 1'b1;
			PCSrc    = 1'b0;
			MemToReg = 1'b0;
			ALUop	 = 2'b00;
		end
	
		if(po == 6'd19) //branch conditional
        begin
		    MemRead  = 1'b0;
			MemWrite = 1'b0;
			RegWrite = 1'b0;
			RegRead  = 1'b1;
			Branch   = 1'b1;
			ALUSrc   = 1'b0;
			PCSrc    = 1'b1;
			MemToReg = 1'b0;
			ALUop	 = 2'b01 ;
		end
		if(po == 6'd18) //branch unconditional
        begin
		    MemRead  = 1'b0;
			MemWrite = 1'b0;
			RegWrite = 1'b0;
			RegRead  = 1'b0;
			Branch   = 1'b1;
			ALUSrc   = 1'b0;
			PCSrc    = 1'b1;
			MemToReg = 1'b0;
			ALUop	 = 2'b00;
		end
    end
endmodule

Assignments A3 _ and A4 - uPower/A4 - uPower/parse_instruction.v
/* Module designed to read the instruction and assign the various
   components of the instruction to suitable variables depending on the format
*/

module parse_instruction(
    output wire [5:0] po, 
    output reg [4:0] rs, rt, rd, bo, bi, 
    output reg aa, lk, rc, oe,
    output reg [9:0] xox,
    output reg [8:0] xoxo, 
    output reg [15:0] si, 
    output reg [13:0] bd,
	output reg [63:0] ds,
    output reg [1:0] xods, 
    output reg [23:0] li,
    input [31:0] instruction, p_count
);

    assign po = instruction[31:26];

    always @(instruction) 
    begin
        rs = 5'b00000;
        rt = 5'b00000;
        rd = 5'b00000;
        bo = 5'b00000;
        bi = 5'b00000;
        aa = 1'b0;
        lk = 1'b0;
        rc = 1'b0;
        oe = 1'b0;
        xox = 10'b0000000000;
        xoxo = 9'b000000000;
        si = 16'b0000000000000000;
        bd = 14'b00000000000000;
        ds = 64'b00000000000000;
        xods = 2'b00;
        li = 24'b000000000000000000000000;
        //XO
        if(po == 6'd31 & (instruction[9:1] == 9'd266 | instruction[9:1] == 9'd40))
        begin
            // $display("HI\n");
            rd = instruction[25:21];
            rs = instruction[20:16];
            rt = instruction[15:11];
            oe = instruction[10];
            xoxo = instruction[9:1];
            rc = instruction[0];
        end

        //X
        else if(po == 6'd31)
        begin
            rd = instruction[25:21];
            rs = instruction[20:16];
            rt = instruction[15:11];
            xox = instruction[10:1];
            rc = instruction[0];
        end

        //D
       /* else if(po == 6'd14 | po == 6'd15 | po == 6'd28 | po == 6'd24 | po == 6'd26 | po == 6'd32 | po == 6'd36 | po == 6'd37 |po == 6'd40 | po == 6'd42 |po == 6'd44 |po == 6'd34 |po == 6'd38)
        begin
            rd = instruction[25:21];
            rs = instruction[20:16];   
            si = instruction[15:0];
            // $display("RD : %5b\n, RS : %5b\n", rd, rs);
        end*/

        //B
        else if(po == 6'd19)
        begin
            bo = instruction[25:21];
            bi = instruction[20:16];
            bd = instruction[15:2];
            aa = instruction[1];
            lk = instruction[0];
        end

        //I
        else if(po == 6'd18)
        begin
            li = instruction[25:2];
            aa = instruction[1];
            lk = instruction[0];
        end 

        //DS
        else
        begin
            rd = instruction[25:21];
            rs = instruction[20:16];
            ds = $signed(instruction[15:2]);
			//ds = {{50{instruction[15]}},instruction[15:2]};
			//$display("LALALAL %64b \n",ds);
            xods = instruction[1:0];
        end
    end
endmodule

Assignments A3 _ and A4 - uPower/A4 - uPower/Instruction_read.v
/*  This module is used to read the 32 bit uPower instructions from the instructions.mem file
*/

module read_instructions(instruction, program_counter);

    input [31:0] program_counter;
    output reg [31:0] instruction;

    reg [31:0] instructions[0:7];     //set to the number of instructions in the file

    initial begin
        $readmemb("instructions.mem", instructions, 0, 7);
    end

    always @ (program_counter) begin
        instruction = instructions[program_counter];
        $display("Instruction : %32b \n PC : %32b\n", instruction, program_counter);
    end

endmodule

Assignments A3 _ and A4 - uPower/A4 - uPower/uPowerDatapath.v
/* uPowerISA Core Module is the centre of all operations that handles all the operations and instantiates
all the necessary modules
*/
`include "uPower_Control_Unit.v"
`include "parse_instruction.v"
`include "ALU64Bit.v"
`include "uPowerALUControl.v"
`include "Instruction_read.v"
`include "Memory_read_write.v"
`include "Register_read_write.v"

module uPowerDatapath(clock);

input clock; //Execution happens only at positive level-transition (edge sensitive)

//Program counter

reg [31:0] PC = 32'b0;

//Instruction
wire [31:0] instruction;

//Parse instruction
wire [5:0] po;
wire [4:0] rs,rt,rd,bo,bi;
wire [8:0] xoxo;
wire [9:0] xox;
wire rc,aa,lk,oe;
wire [13:0] bd;
wire [63:0] ds;
wire [15:0] si;
wire [23:0] li;
wire [1:0] xods;
wire [3:0] ALUInput;

//Signals

wire RegRead, RegWrite;
wire MemRead, MemWrite, MemToReg;
wire Branch, ALUSrc, PCSrc;
wire [1:0] ALUop;

//Register contents
wire [63:0] write_data, rs_content, rt_content, rd_content, memory_read_data;

//Modules are instantiated
read_instructions p1(instruction, PC);
parse_instruction p2(po, rs, rt, rd, bo, bi, aa, lk, rc, oe, xox, xoxo, si, bd, ds, xods, li, instruction, PC);
control_unit p3(RegRead, RegWrite, MemRead, MemWrite, Branch, MemToReg, ALUSrc, PCSrc, ALUop, po);
ALU_Control p4(ALUInput, ALUop, xox,xoxo,xods);
ALU64bit p5(write_data, flag, ALUSrc, ALUInput, rs_content, rt_content, ds);
read_write_memory p6(memory_read_data, write_data, rd_content, rd, po, MemWrite, MemRead);
read_write_registers p7(rs_content, rt_content, rd_content, memory_read_data, write_data, rs, rt, rd, bo, bi, po, RegRead, RegWrite, MemToReg, clock);

// Updating the PC value

always @(posedge clock) 
 begin
     
     if(flag == 1 & Branch == 1 & aa == 0 & po == 6'd19)           //Branch Conditional
       PC = PC + 1 + $signed(bd);

     else if(flag == 1 & Branch == 1 & aa == 1 & po == 6'd19) begin //Branch Absolute
       PC = $signed(bd);
	   end

     else if(Branch == 1 & aa == 1 & po == 6'd18)
       PC = $signed(li);

     else if(Branch == 1 & aa == 0 & po == 6'd18)
       PC = PC + 1 + $signed(li);
     else 
       PC = PC + 1;
 end


endmodule

Assignments A3 _ and A4 - uPower/A4 - uPower/uPowerDatapath_tb.v
/* Testbenchh for the uPower Datapath */
`include "uPowerDatapath.v"

module tb_uPowerDatapath();

reg clk;

uPowerDatapath tb(clk);

initial 
begin 
    clk = 1'b0;
    #829 $finish;
end

initial
begin
	$dumpfile("upowerdatapath.vcd");
	$dumpvars(0,tb_uPowerDatapath);
end

always begin 
    #10 clk = ~clk;
end

endmodule

Assignments A3 _ and A4 - uPower/A4 - uPower/upowerdatapath.vcd
$date
	Sat Jun 06 17:14:12 2020
$end
$version
	Icarus Verilog
$end
$timescale
	1s
$end
$scope module tb_uPowerDatapath $end
$var reg 1 ! clk $end
$scope module tb $end
$var wire 1 ! clock $end
$var wire 9 " xoxo [8:0] $end
$var wire 10 # xox [9:0] $end
$var wire 2 $ xods [1:0] $end
$var wire 64 % write_data [63:0] $end
$var wire 16 & si [15:0] $end
$var wire 64 ' rt_content [63:0] $end
$var wire 5 ( rt [4:0] $end
$var wire 64 ) rs_content [63:0] $end
$var wire 5 * rs [4:0] $end
$var wire 64 + rd_content [63:0] $end
$var wire 5 , rd [4:0] $end
$var wire 1 - rc $end
$var wire 6 . po [5:0] $end
$var wire 1 / oe $end
$var wire 64 0 memory_read_data [63:0] $end
$var wire 1 1 lk $end
$var wire 24 2 li [23:0] $end
$var wire 32 3 instruction [31:0] $end
$var wire 1 4 flag $end
$var wire 64 5 ds [63:0] $end
$var wire 5 6 bo [4:0] $end
$var wire 5 7 bi [4:0] $end
$var wire 14 8 bd [13:0] $end
$var wire 1 9 aa $end
$var wire 1 : RegWrite $end
$var wire 1 ; RegRead $end
$var wire 1 < PCSrc $end
$var wire 1 = MemWrite $end
$var wire 1 > MemToReg $end
$var wire 1 ? MemRead $end
$var wire 1 @ Branch $end
$var wire 2 A ALUop [1:0] $end
$var wire 1 B ALUSrc $end
$var wire 4 C ALUInput [3:0] $end
$var reg 32 D PC [31:0] $end
$scope module p1 $end
$var wire 32 E program_counter [31:0] $end
$var reg 32 F instruction [31:0] $end
$upscope $end
$scope module p2 $end
$var wire 32 G instruction [31:0] $end
$var wire 32 H p_count [31:0] $end
$var wire 6 I po [5:0] $end
$var reg 1 9 aa $end
$var reg 14 J bd [13:0] $end
$var reg 5 K bi [4:0] $end
$var reg 5 L bo [4:0] $end
$var reg 64 M ds [63:0] $end
$var reg 24 N li [23:0] $end
$var reg 1 1 lk $end
$var reg 1 / oe $end
$var reg 1 - rc $end
$var reg 5 O rd [4:0] $end
$var reg 5 P rs [4:0] $end
$var reg 5 Q rt [4:0] $end
$var reg 16 R si [15:0] $end
$var reg 2 S xods [1:0] $end
$var reg 10 T xox [9:0] $end
$var reg 9 U xoxo [8:0] $end
$upscope $end
$scope module p3 $end
$var wire 6 V po [5:0] $end
$var reg 1 B ALUSrc $end
$var reg 2 W ALUop [1:0] $end
$var reg 1 @ Branch $end
$var reg 1 ? MemRead $end
$var reg 1 > MemToReg $end
$var reg 1 = MemWrite $end
$var reg 1 < PCSrc $end
$var reg 1 ; RegRead $end
$var reg 1 : RegWrite $end
$upscope $end
$scope module p4 $end
$var wire 2 X ALUop [1:0] $end
$var wire 2 Y xods [1:0] $end
$var wire 10 Z xox [9:0] $end
$var wire 9 [ xoxo [8:0] $end
$var reg 4 \ ALUInput [3:0] $end
$upscope $end
$scope module p5 $end
$var wire 4 ] ALUInput [3:0] $end
$var wire 1 B ALUSrc $end
$var wire 64 ^ ds [63:0] $end
$var wire 64 _ rt_content [63:0] $end
$var wire 64 ` rs_content [63:0] $end
$var reg 64 a ALU_result [63:0] $end
$var reg 1 4 flag $end
$var reg 64 b signed_rs [63:0] $end
$var reg 64 c signed_rt [63:0] $end
$upscope $end
$scope module p6 $end
$var wire 1 ? MemRead $end
$var wire 1 = MemWrite $end
$var wire 64 d address [63:0] $end
$var wire 6 e po [5:0] $end
$var wire 5 f rd [4:0] $end
$var wire 64 g write_data [63:0] $end
$var reg 64 h read_data [63:0] $end
$upscope $end
$scope module p7 $end
$var wire 1 > MemToReg $end
$var wire 1 ; RegRead $end
$var wire 1 : RegWrite $end
$var wire 5 i bi [4:0] $end
$var wire 5 j bo [4:0] $end
$var wire 1 ! clk $end
$var wire 6 k po [5:0] $end
$var wire 5 l rd [4:0] $end
$var wire 64 m read_mem_data [63:0] $end
$var wire 5 n rs [4:0] $end
$var wire 5 o rt [4:0] $end
$var wire 64 p write_data [63:0] $end
$var reg 64 q read_data_1 [63:0] $end
$var reg 64 r read_data_2 [63:0] $end
$var reg 64 s read_data_3 [63:0] $end
$upscope $end
$upscope $end
$upscope $end
$enddefinitions $end
#0
$dumpvars
b0 s
bx r
b0 q
b1 p
b0 o
b0 n
b111 m
b1 l
b111010 k
b0 j
b0 i
b111 h
b0 g
b1 f
b111010 e
b1 d
b1 c
b0 b
b1 a
b0 `
bx _
b1 ^
b10 ]
b10 \
b0 [
b0 Z
b0 Y
b0 X
b0 W
b111010 V
b0 U
b0 T
b0 S
b0 R
b0 Q
b0 P
b1 O
b0 N
b1 M
b0 L
b0 K
b0 J
b111010 I
b0 H
b11101000001000000000000000000100 G
b11101000001000000000000000000100 F
b0 E
b0 D
b10 C
1B
b0 A
0@
1?
1>
0=
0<
1;
1:
09
b0 8
b0 7
b0 6
b1 5
x4
b11101000001000000000000000000100 3
b0 2
01
b111 0
0/
b111010 .
0-
b1 ,
b0 +
b0 *
b0 )
b0 (
bx '
b0 &
b1 %
b0 $
b0 #
b0 "
0!
$end
#10
b10 C
b10 \
b10 ]
bx %
bx a
bx d
bx p
bx c
0>
0B
0;
0:
0?
bx $
bx S
bx Y
bx *
bx P
bx n
bx 5
bx M
bx ^
bx ,
bx O
bx f
bx l
bx .
bx I
bx V
bx e
bx k
bx 3
bx F
bx G
b1 D
b1 E
b1 H
1!
#20
0!
#30
b10 D
b10 E
b10 H
1!
#40
0!
#50
b11 D
b11 E
b11 H
1!
#60
0!
#70
b100 D
b100 E
b100 H
1!
#80
0!
#90
b101 D
b101 E
b101 H
1!
#100
0!
#110
b110 D
b110 E
b110 H
1!
#120
0!
#130
b111 D
b111 E
b111 H
1!
#140
0!
#150
b1000 D
b1000 E
b1000 H
1!
#160
0!
#170
b1001 D
b1001 E
b1001 H
1!
#180
0!
#190
b1010 D
b1010 E
b1010 H
1!
#200
0!
#210
b1011 D
b1011 E
b1011 H
1!
#220
0!
#230
b1100 D
b1100 E
b1100 H
1!
#240
0!
#250
b1101 D
b1101 E
b1101 H
1!
#260
0!
#270
b1110 D
b1110 E
b1110 H
1!
#280
0!
#290
b1111 D
b1111 E
b1111 H
1!
#300
0!
#310
b10000 D
b10000 E
b10000 H
1!
#320
0!
#330
b10001 D
b10001 E
b10001 H
1!
#340
0!
#350
b10010 D
b10010 E
b10010 H
1!
#360
0!
#370
b10011 D
b10011 E
b10011 H
1!
#380
0!
#390
b10100 D
b10100 E
b10100 H
1!
#400
0!
#410
b10101 D
b10101 E
b10101 H
1!
#420
0!
#430
b10110 D
b10110 E
b10110 H
1!
#440
0!
#450
b10111 D
b10111 E
b10111 H
1!
#460
0!
#470
b11000 D
b11000 E
b11000 H
1!
#480
0!
#490
b11001 D
b11001 E
b11001 H
1!
#500
0!
#510
b11010 D
b11010 E
b11010 H
1!
#520
0!
#530
b11011 D
b11011 E
b11011 H
1!
#540
0!
#550
b11100 D
b11100 E
b11100 H
1!
#560
0!
#570
b11101 D
b11101 E
b11101 H
1!
#580
0!
#590
b11110 D
b11110 E
b11110 H
1!
#600
0!
#610
b11111 D
b11111 E
b11111 H
1!
#620
0!
#630
b100000 D
b100000 E
b100000 H
1!
#640
0!
#650
b100001 D
b100001 E
b100001 H
1!
#660
0!
#670
b100010 D
b100010 E
b100010 H
1!
#680
0!
#690
b100011 D
b100011 E
b100011 H
1!
#700
0!
#710
b100100 D
b100100 E
b100100 H
1!
#720
0!
#730
b100101 D
b100101 E
b100101 H
1!
#740
0!
#750
b100110 D
b100110 E
b100110 H
1!
#760
0!
#770
b100111 D
b100111 E
b100111 H
1!
#780
0!
#790
b101000 D
b101000 E
b101000 H
1!
#800
0!
#810
b101001 D
b101001 E
b101001 H
1!
