Assignments A3 _ A4 - MIPS/A4 - MIPS/Register_read_write.v
/* This module is used to read and write into the 32 bit register file
*/
module read_write_registers(
    output reg [31:0] read_data_1, read_data_2,   // The output are two 32-bit binary numbers that contain the data stored in RS and RT
    input [31:0] read_mem_data, write_data,   // The data to be written
    input [4:0] rs, rt, rd,    // RS and RT are the read registers and RD (Destination register) is the write register
    input [5:0] opcode,        
    input RegRead, RegWrite, RegDst, MemToReg, clk   // Signals to perform operations
);

    reg [31:0] registers [31:0];    // The set of 32 registers (32-bit)
	
    initial begin
        $readmemb("registers.mem", registers);   //Reads all the values stored in the 32 registers
    end
	
    always @(rd, read_mem_data,write_data) begin    // If a change in the data to be written is noticed
        if(RegWrite) begin
            /* RegDst = 0 => Write to RT
               RegDst = 1 => Write to RD
            */
            if(RegDst) begin
				if(MemToReg) begin //Store data read from memory in rd
					if(opcode == 6'h24)begin
						registers[rd][7:0] = read_mem_data[7:0];
					end
					if(opcode == 6'h25)begin
						registers[rd][15:0] = read_mem_data[15:0];
					end
					else begin
						registers[rd] = read_mem_data;
					end
				end
				else begin //Store data from ALU in rd
					if(opcode == 6'h24)begin
						registers[rd][7:0] = write_data[7:0];
					end
					if(opcode == 6'h25)begin
						registers[rd][15:0] = write_data[15:0];
					end
					else begin
						registers[rd] = write_data;
					end				
				end
            end
            else begin
				if(MemToReg) begin //Store data read from memory in rt
					if(opcode == 6'h24)begin        
						registers[rt][7:0] = read_mem_data[7:0];
					end
					if(opcode == 6'h25)begin       
						registers[rt][15:0] = read_mem_data[15:0];
					end
					else begin
						registers[rt] = read_mem_data;
					end				
				end
				else begin //Store data from ALU in rt
					if(opcode == 6'h24)begin        
						registers[rt][7:0] = write_data[7:0];
					end
					if(opcode == 6'h25)begin        
						registers[rt][15:0] = write_data[15:0];
					end
					else begin
						registers[rt] = write_data;
					end
				end
            end

            // Write back the updated values to the registers file
            $writememb("registers.mem",registers);
        end
    end

    always @(rs, rt) begin
        // Read from registers
        if(RegRead) begin
            read_data_1 = registers[rs];
            read_data_2 = registers[rt];
        end
    end
endmodule

Assignments A3 _ A4 - MIPS/A4 - MIPS/Memory_read_write.v
/* This module is used to read and write the data.mem file(Main Memory)
*/

module read_write_memory(
    output reg [31:0] read_data,  //The data read from the main memory
    input  [31:0] address, write_data, //The ADDRESS and WRITE_DATA are inputs
    input [5:0] opcode,
    input MemRead,MemWrite    // Signals for Memory read and write
);
	
	// Stores the contents of the main memory
    reg [31:0] data_mem [0:31];   
	
	//Read the main memory contents
    initial    
    begin
        $readmemb("data.mem", data_mem, 0,31); 
    end
	
    always @(address) begin
        if(MemWrite) begin
            if(opcode == 6'h28) begin
                data_mem[address][7:0] = write_data[7:0];
            end 
            else if(opcode == 6'h29) begin
                data_mem[address][15:0] = write_data[15:0];
            end
            else begin
                data_mem[address] = write_data;
            end
            // Write the updated contents back to the memory file
            $writememb("data.mem", data_mem);
        end
    end
	
    always @(address) begin
        if(MemRead) begin
            read_data = data_mem[address];
        end
    end	

endmodule

Assignments A3 _ A4 - MIPS/A4 - MIPS/ALU32bit.v
/* Module designed to act as the ALU 
*/

module ALU32bit(ALU_result, flag, rs, rt, rs_content, rt_content, immediate, ALUSrc, ALUInput);
	
    input [31:0] rs_content, rt_content; //inputs
    input [4:0] rs, rt;
	input [31:0] immediate;
	input [3:0] ALUInput;
	input ALUSrc;
    output reg flag;
    output reg [31:0] ALU_result; //Output of the ALU
	
    reg signed [31:0] signed_rs, signed_rt; 

    always @ (ALUInput, rs_content, rt_content) begin
		
		
        // Signed value assignment
        signed_rs = rs_content;
		
		//Assign second input of ALU as immediated value or rt from registers depending on ALUSrc
		if(ALUSrc) begin
			signed_rt = immediate;
		end
		else
			signed_rt = rt_content;
						
            case(ALUInput)
			
                4'b0010 : //ADD
                    begin
                    ALU_result = signed_rs + signed_rt;
                    end

                4'b0110 : //SUB - Subtract
					begin
                    ALU_result = signed_rs - signed_rt;
					if(ALU_result == 0) 
						flag = 1'b1;
					else
						flag = 1'b0;
					end

                4'b0000 : //AND
                    ALU_result = rs_content & rt_content;
					
                4'b0001 : //OR
                    ALU_result = rs_content | rt_content;
					
                4'b1100 : //NOR
                    ALU_result = ~(rs_content | rt_content);
					
                4'b0111 : //SLT - Set less than
                    begin
                        if(signed_rs < signed_rt) begin
                            ALU_result = 1;
                        end else begin
                            ALU_result = 0;
                        end
                    end
			
            endcase
    end

	initial begin
        $monitor("RS : %32b, RT/Immediate : %32b, Result : %32b\n", rs_content, signed_rt, ALU_result);
    end
	
endmodule

Assignments A3 _ A4 - MIPS/A4 - MIPS/ALUcontrol.v
// Module to behave like the ALU control unit to output the ALU control signal  

module alu_control_unit(
    output reg [3:0] ALUInput,
    input [5:0] funct,
	input [1:0] ALUop
);

    initial begin
        ALUInput  = 4'b0000;	
    end
	
    always @(ALUop, funct) 
    begin
        ALUInput  = 4'b0000;	
	
        if(ALUop == 2'b00) begin
			ALUInput = 4'b0010; 
        end
        else if(ALUop == 2'b01) begin
            ALUInput  = 4'b0110; 
        end
        else if(ALUop == 2'b10) begin //rtype
			if(funct == 6'b100000) begin //add
				ALUInput = 4'b0010;
			end
			if(funct == 6'b100010) begin //subtract
				ALUInput = 4'b0110;
			end
			if(funct == 6'b100100) begin //and
				ALUInput = 4'b0000;
			end
			if(funct == 6'b100101) begin //or
				ALUInput = 4'b0001;
			end
			if(funct == 6'b101010) begin //slt
				ALUInput = 4'b0111;
			end
        end
    end	
endmodule

Assignments A3 _ A4 - MIPS/A4 - MIPS/Control_Unit.v
/* Module to behave like the control unit to set the necessary signals for the execution of an 
   instruction -
   1. RegDst - Which field of the instruction is the register to be written to
   2. RegWrite - Write to register file
   3. RegRead - Read from a register
   4. ALUSrc - The source for the second input to the ALU
   5. PCSrc - Source for PC (next instruction to be executed)
   6. MemRead - Read from the main memory
   7. MemWrite - Write to the main memory
   8. MemToReg - Source of write_data (data to be written to the register file)
   9. Branch -  When a branch/jump instruction is used
*/
module control_unit(
    output reg  RegRead,
                RegWrite,
                MemRead,
                MemWrite,
                RegDst, // if this is 0 select rt, otherwise select rd
                Branch,
				BranchNE,
                ALUSrc,
                PCSrc,
                MemToReg,
	output reg [1:0] ALUop,
    input [5:0] opcode, funct
);

    initial begin
        MemRead  = 1'b0;
        MemWrite = 1'b0;
        RegWrite = 1'b0;
        RegRead  = 1'b0;
        RegDst   = 1'b0;
        Branch   = 1'b0;
        ALUSrc   = 1'b0;
        PCSrc    = 1'b0;
        MemToReg = 1'b0;
		BranchNE = 1'b0;
		ALUop	 = 2'b00;
		
    end
	
    always @(opcode, funct) 
    begin
	    // Reset the signals to 0
        MemRead  = 1'b0;
        MemWrite = 1'b0;
        RegWrite = 1'b0;
        RegRead  = 1'b0;
        RegDst   = 1'b0;
        Branch   = 1'b0;
		BranchNE = 1'b0;
        ALUSrc   = 1'b0;
        PCSrc    = 1'b0;
        MemToReg = 1'b0;
		ALUop	 = 2'b00;
		
        // R type
        if(opcode == 6'h0) begin
			MemRead 		= 1'b0;
			MemWrite 		= 1'b0;
			RegWrite 		= 1'b1;
			RegRead  		= 1'b1;
			RegDst   		= 1'b1;
			Branch   		= 1'b0;
			ALUSrc   		= 1'b0;
			PCSrc    		= 1'b0;
			MemToReg 		= 1'b0;
			ALUop	 		= 2'b10;
            // If NOT JR  - Jump Register
            //if(funct != 6'h08) begin
              //  RegWrite = 1'b1;
            //end
        end
		else if(opcode == 6'h23) begin // lw
			MemRead  		= 1'b1;
			MemWrite 		= 1'b0;
			RegWrite 		= 1'b1;
			RegRead  		= 1'b1;
			RegDst   		= 1'b0;
			Branch		    = 1'b0;
			ALUSrc   		= 1'b1;
			PCSrc    		= 1'b0;
			MemToReg 		= 1'b1;
			ALUop	 		= 2'b00;
		end
		
		else if(opcode == 6'h2b) begin //sw
	        MemRead  = 1'b0;
			MemWrite = 1'b1;
			RegWrite = 1'b0;
			RegRead  = 1'b1;
			RegDst   = 1'b0;
			Branch   = 1'b0;
			ALUSrc   = 1'b1;
			PCSrc    = 1'b0;
			MemToReg = 1'b0;
			ALUop	 = 2'b00;
		end
		
		else if(opcode == 6'h8) begin //addi
			MemRead  		= 1'b0;
			MemWrite 		= 1'b0;
			RegWrite 		= 1'b1;
			RegRead  		= 1'b1;
			RegDst   		= 1'b0;
			Branch   		= 1'b0;
			ALUSrc   		= 1'b1;
			PCSrc    		= 1'b0;
			MemToReg 		= 1'b0;
			ALUop	 		= 2'b00;
		end
		
		else if(opcode == 6'h4) begin //beq
			MemRead  		= 1'b0;
			MemWrite 		= 1'b0;
			RegWrite 		= 1'b0;
			RegRead  		= 1'b1;
			RegDst   		= 1'b0;
			Branch	        = 1'b1;
			ALUSrc   		= 1'b0;
			PCSrc    		= 1'b1;
			MemToReg 		= 1'b1;
			ALUop	 		= 2'b01;
		end
		
		else if(opcode == 6'h5) begin //bne
			MemRead  		= 1'b0;
			MemWrite 		= 1'b0;
			RegWrite 		= 1'b0;
			RegRead  		= 1'b1;
			RegDst   		= 1'b0;
			BranchNE        = 1'b1;
			ALUSrc   		= 1'b0;
			PCSrc    		= 1'b1;
			MemToReg 		= 1'b1;
			ALUop	 		= 2'b01;
		end
	
		//lw
        // LUI(load unsigned immediate) => no need to read any register => immediate value is written to a register
       /* else if(opcode == 6'b001111) begin
            RegWrite = 1'b1;
            ALUSrc   = 1'b1;
        end
        // If r-type, don't enter this block
        // For r-type, beq, bne, sb, sh and sw there is no need to register write
        else if(opcode != 6'h0 & opcode != 6'h4 & opcode != 6'h5 & opcode != 6'h28 & opcode != 6'h29 & opcode != 6'h2b) begin
            RegWrite = 1'b1;
        end
        // For branch instructions
        else if(opcode == 6'h4 | opcode == 6'h5) begin
            Branch   = 1'b1;
			RegRead  = 1'b1;
			ALUop 	 = 2'b01;
        end
        // For memory write operation
        // sb, sh and sw use memory to write
        else if(opcode != 6'h0 & (opcode == 6'h28 | opcode == 6'h29 | opcode == 6'h2b)) begin
            MemWrite = 1'b1;
            RegRead  = 1'b1;
            ALUSrc   = 1'b1;
			//ALUop	 = 2'b00;
        end
        // For memory read operation
        // lw, 
        else if(opcode != 6'h0 & (opcode == 6'h23))begin
            MemRead = 1'b1;
            ALUSrc  = 1'b1;
            MemToReg= 1'b1;
            RegWrite= 1'b1;
            RegRead  = 1'b1;
			ALUop = 2'b00;

        end
        // J type
       /* else
        begin
            PCSrc = 1'b1;
        end*/
    end
	
	
	
endmodule

Assignments A3 _ A4 - MIPS/A3 - MIPS/Module 3 - Instruction Fetch/parse_instruction.v
/* Module designed to read the instruction and assign the various
   components of the instruction to suitable variables depending on the format
*/
module parse_instruction(
    output wire [5:0] opcode,
    output reg [4:0] rs, rt, rd, shamt, 
    output reg [5:0] funct,
    output reg[31:0] extended_immediate,
    output reg [25:0] address,
    input [31:0] instruction, p_count
);

    assign opcode = instruction[31:26];
	
    always @(instruction) begin
        if(opcode == 6'h0) 
        begin        //R-type 
            shamt = instruction[10:6];
            rd = instruction[15:11];
            rt = instruction[20:16];
            rs = instruction[25:21];
            funct = instruction[5:0];
        end
        else if(opcode == 6'h2 | opcode == 6'h3) 
        begin   // J-type
            address = instruction[25:0];
        end
        else 
        begin                               // I-type
            rt = instruction[20:16];
            rs = instruction[25:21];
			extended_immediate = $signed(instruction[15:0]);

        end
    end
	
endmodule

Assignments A3 _ A4 - MIPS/A4 - MIPS/Instruction_read.v
/* This module is used to read the 32 bit MIPS instructions from the instructions.mem file
*/
module read_instructions(instruction, program_counter);

    input [31:0] program_counter;
    output reg [31:0] instruction;
	
    reg [31:0] instructions[0:6];  //set to the number of instructions in the file
	
    initial begin 
        $readmemb("instructions.mem", instructions, 0,6); 
    end
	
    always @ (program_counter) begin
        instruction = instructions[program_counter];
        $display("Instruction : %32b , PC : %32b", instruction, program_counter);
    end

endmodule

Assignments A3 _ A4 - MIPS/A4 - MIPS/Datapath.v
/* MIPS Core Module is the centre of all operations that handles all the operations and instantiates
   all the necessary modules
*/
`include "Control_unit.v"
`include "Register_read_write.v"
`include "ALU32bit.v"
`include "ALUcontrol.v"
`include "Instruction_read.v"
`include "Memory_read_write.v"
`include "parse_instruction.v"


module Datapath(clock);

    input clock;   // Execution happens only at positive level-transition (edge sensitive)
	
    // Program counter
    reg[31:0] PC = 32'b0; 
	
    // Instruction
    wire [31:0] instruction;
	
    // Parse instruction
    wire [5:0] funct;
    wire [4:0] rs, rt, rd, shamt;
    wire [25:0] address;
    wire [31:0] immediate;
    wire [5:0] opcode;
	wire [3:0] ALUInput;
	
    // Signals
    wire RegRead, RegWrite, RegDst;  
    wire MemRead, MemWrite, MemToReg;
    wire Branch, BranchNE;
	wire flag;
    wire PCSrc, ALUSrc;
	wire [1:0] ALUop;
	
    // Registers contents
    wire [31:0] write_data, rs_content, rt_content, memory_read_data;
	
	// Control signals for Load Instruction
	/*initial begin
	MemRead  		= 1'b0;
    MemWrite 		= 1'b0;
    RegWrite 		= 1'b0;
    RegRead  		= 1'b1;
    RegDst   		= 1'b0;
    branch_signal   = 1'b1;
    ALUSrc   		= 1'b0;
    PCSrc    		= 1'b1;
    MemToReg 		= 1'b1;
	ALUop	 		= 2'b01;
	end*/
	
    // Instantiating all necessary modules
    read_instructions p1 (instruction, PC);
    parse_instruction p2 (opcode, rs, rt, rd, shamt, funct, immediate, address, instruction, PC);
	control_unit p7 (RegRead, RegWrite, MemRead, MemWrite, RegDst, Branch,BranchNE, ALUSrc,PCSrc,MemToReg,ALUop,opcode,funct);
	alu_control_unit p3 (ALUInput, funct, ALUop);
    ALU32bit p4 (write_data, flag, rs, rt, rs_content, rt_content, immediate, ALUSrc, ALUInput);
    read_write_memory p5 (memory_read_data, write_data, rt_content, opcode, MemRead, MemWrite);
    read_write_registers p6 (rs_content, rt_content, memory_read_data, write_data, rs, rt, rd, opcode, RegRead, RegWrite, RegDst, MemToReg, clock);
	
    // PC operations - The next instruction is read only when the clock is at positive edge
    always @(posedge clock) begin 
        if(Branch == 1 & flag == 1) begin
            PC = PC + 1 + $signed(immediate); 
        end
		else if(BranchNE == 1 & flag == 0) begin
            PC = PC + 1 + $signed(immediate); 
        end
		else
            PC = PC + 1;
    end 
endmodule

Assignments A3 _ A4 - MIPS/A4 - MIPS/Datapath_tb.v
// MIPS test bench - To drive and simulate the entire MIPS ALU 
`include "Datapath.v"
module tb_Datapath ();

    reg clk;
    wire result;

    Datapath tb(.clock(clk));

    initial 
    begin 

        clk = 1'b0;
        #7990 $finish;
    end
	
	initial
	begin
		$dumpfile("datapath.vcd");
		$dumpvars(0,tb_Datapath);
	end

    always begin 
        #100 clk = ~clk;
    end

endmodule

Assignments A3 _ A4 - MIPS/A4 - MIPS/datapath.vcd
$date
	Sat Jun 06 18:05:29 2020
$end
$version
	Icarus Verilog
$end
$timescale
	1s
$end
$scope module tb_Datapath $end
$var reg 1 ! clk $end
$scope module tb $end
$var wire 1 ! clock $end
$var wire 32 " write_data [31:0] $end
$var wire 5 # shamt [4:0] $end
$var wire 32 $ rt_content [31:0] $end
$var wire 5 % rt [4:0] $end
$var wire 32 & rs_content [31:0] $end
$var wire 5 ' rs [4:0] $end
$var wire 5 ( rd [4:0] $end
$var wire 6 ) opcode [5:0] $end
$var wire 32 * memory_read_data [31:0] $end
$var wire 32 + instruction [31:0] $end
$var wire 32 , immediate [31:0] $end
$var wire 6 - funct [5:0] $end
$var wire 1 . flag $end
$var wire 26 / address [25:0] $end
$var wire 1 0 RegWrite $end
$var wire 1 1 RegRead $end
$var wire 1 2 RegDst $end
$var wire 1 3 PCSrc $end
$var wire 1 4 MemWrite $end
$var wire 1 5 MemToReg $end
$var wire 1 6 MemRead $end
$var wire 1 7 BranchNE $end
$var wire 1 8 Branch $end
$var wire 2 9 ALUop [1:0] $end
$var wire 1 : ALUSrc $end
$var wire 4 ; ALUInput [3:0] $end
$var reg 32 < PC [31:0] $end
$scope module p1 $end
$var wire 32 = program_counter [31:0] $end
$var reg 32 > instruction [31:0] $end
$upscope $end
$scope module p2 $end
$var wire 32 ? instruction [31:0] $end
$var wire 32 @ p_count [31:0] $end
$var wire 6 A opcode [5:0] $end
$var reg 26 B address [25:0] $end
$var reg 32 C extended_immediate [31:0] $end
$var reg 6 D funct [5:0] $end
$var reg 5 E rd [4:0] $end
$var reg 5 F rs [4:0] $end
$var reg 5 G rt [4:0] $end
$var reg 5 H shamt [4:0] $end
$upscope $end
$scope module p3 $end
$var wire 6 I funct [5:0] $end
$var wire 2 J ALUop [1:0] $end
$var reg 4 K ALUInput [3:0] $end
$upscope $end
$scope module p4 $end
$var wire 4 L ALUInput [3:0] $end
$var wire 32 M immediate [31:0] $end
$var wire 5 N rs [4:0] $end
$var wire 5 O rt [4:0] $end
$var wire 32 P rt_content [31:0] $end
$var wire 32 Q rs_content [31:0] $end
$var wire 1 : ALUSrc $end
$var reg 32 R ALU_result [31:0] $end
$var reg 1 . flag $end
$var reg 32 S signed_rs [31:0] $end
$var reg 32 T signed_rt [31:0] $end
$upscope $end
$scope module p5 $end
$var wire 32 U address [31:0] $end
$var wire 6 V opcode [5:0] $end
$var wire 32 W write_data [31:0] $end
$var wire 1 4 MemWrite $end
$var wire 1 6 MemRead $end
$var reg 32 X read_data [31:0] $end
$upscope $end
$scope module p6 $end
$var wire 1 ! clk $end
$var wire 6 Y opcode [5:0] $end
$var wire 5 Z rd [4:0] $end
$var wire 32 [ read_mem_data [31:0] $end
$var wire 5 \ rs [4:0] $end
$var wire 5 ] rt [4:0] $end
$var wire 32 ^ write_data [31:0] $end
$var wire 1 0 RegWrite $end
$var wire 1 1 RegRead $end
$var wire 1 2 RegDst $end
$var wire 1 5 MemToReg $end
$var reg 32 _ read_data_1 [31:0] $end
$var reg 32 ` read_data_2 [31:0] $end
$upscope $end
$scope module p7 $end
$var wire 6 a funct [5:0] $end
$var wire 6 b opcode [5:0] $end
$var reg 1 : ALUSrc $end
$var reg 2 c ALUop [1:0] $end
$var reg 1 8 Branch $end
$var reg 1 7 BranchNE $end
$var reg 1 6 MemRead $end
$var reg 1 5 MemToReg $end
$var reg 1 4 MemWrite $end
$var reg 1 3 PCSrc $end
$var reg 1 2 RegDst $end
$var reg 1 1 RegRead $end
$var reg 1 0 RegWrite $end
$upscope $end
$upscope $end
$upscope $end
$enddefinitions $end
#0
$dumpvars
b0 c
b100011 b
bx a
b0 `
b0 _
b1 ^
b0 ]
b1 \
b111 [
bx Z
b100011 Y
b111 X
b0 W
b100011 V
b1 U
b1 T
b0 S
b1 R
b0 Q
b0 P
b0 O
b1 N
b1 M
b10 L
b10 K
b0 J
bx I
bx H
b0 G
b1 F
bx E
bx D
b1 C
bx B
b100011 A
b0 @
b10001100001000000000000000000001 ?
b10001100001000000000000000000001 >
b0 =
b0 <
b10 ;
1:
b0 9
08
07
16
15
04
03
02
11
10
bx /
x.
bx -
b1 ,
b10001100001000000000000000000001 +
b111 *
b100011 )
bx (
b1 '
b0 &
b0 %
b0 $
bx #
b1 "
0!
$end
#100
05
0:
01
00
06
bx ,
bx C
bx M
bx '
bx F
bx N
bx \
bx %
bx G
bx O
bx ]
bx )
bx A
bx V
bx Y
bx b
bx +
bx >
bx ?
b1 <
b1 =
b1 @
1!
#200
0!
#300
b10 <
b10 =
b10 @
1!
#400
0!
#500
b11 <
b11 =
b11 @
1!
#600
0!
#700
b100 <
b100 =
b100 @
1!
#800
0!
#900
b101 <
b101 =
b101 @
1!
#1000
0!
#1100
b110 <
b110 =
b110 @
1!
#1200
0!
#1300
b111 <
b111 =
b111 @
1!
#1400
0!
#1500
b1000 <
b1000 =
b1000 @
1!
#1600
0!
#1700
b1001 <
b1001 =
b1001 @
1!
#1800
0!
#1900
b1010 <
b1010 =
b1010 @
1!
#2000
0!
#2100
b1011 <
b1011 =
b1011 @
1!
#2200
0!
#2300
b1100 <
b1100 =
b1100 @
1!
#2400
0!
#2500
b1101 <
b1101 =
b1101 @
1!
#2600
0!
#2700
b1110 <
b1110 =
b1110 @
1!
#2800
0!
#2900
b1111 <
b1111 =
b1111 @
1!
#3000
0!
#3100
b10000 <
b10000 =
b10000 @
1!
#3200
0!
#3300
b10001 <
b10001 =
b10001 @
1!
#3400
0!
#3500
b10010 <
b10010 =
b10010 @
1!
#3600
0!
#3700
b10011 <
b10011 =
b10011 @
1!
#3800
0!
#3900
b10100 <
b10100 =
b10100 @
1!
#4000
0!
#4100
b10101 <
b10101 =
b10101 @
1!
#4200
0!
#4300
b10110 <
b10110 =
b10110 @
1!
#4400
0!
#4500
b10111 <
b10111 =
b10111 @
1!
#4600
0!
#4700
b11000 <
b11000 =
b11000 @
1!
#4800
0!
#4900
b11001 <
b11001 =
b11001 @
1!
#5000
0!
#5100
b11010 <
b11010 =
b11010 @
1!
#5200
0!
#5300
b11011 <
b11011 =
b11011 @
1!
#5400
0!
#5500
b11100 <
b11100 =
b11100 @
1!
#5600
0!
#5700
b11101 <
b11101 =
b11101 @
1!
#5800
0!
#5900
b11110 <
b11110 =
b11110 @
1!
#6000
0!
#6100
b11111 <
b11111 =
b11111 @
1!
#6200
0!
#6300
b100000 <
b100000 =
b100000 @
1!
#6400
0!
#6500
b100001 <
b100001 =
b100001 @
1!
#6600
0!
#6700
b100010 <
b100010 =
b100010 @
1!
#6800
0!
#6900
b100011 <
b100011 =
b100011 @
1!
#7000
0!
#7100
b100100 <
b100100 =
b100100 @
1!
#7200
0!
#7300
b100101 <
b100101 =
b100101 @
1!
#7400
0!
#7500
b100110 <
b100110 =
b100110 @
1!
#7600
0!
#7700
b100111 <
b100111 =
b100111 @
1!
#7800
0!
#7900
b101000 <
b101000 =
b101000 @
1!
